np/client/__init__.py
np/client/numpy_client.py
np/client/utils/__init__.py
np/client/utils/alter.py
numpy_flight_client-0.0.3.dist-info/METADATA
numpy_flight_client-0.0.3.dist-info/WHEEL
numpy_flight_client-0.0.3.dist-info/licenses/LICENSE
numpy_flight_client-0.0.3.dist-info/RECORD
