Metadata-Version: 2.4
Name: numpy-flight-client
Version: 0.0.3
Summary: A little client for applications driven by numpy
Project-URL: repository, https://github.com/tschm/numpy-client
Author-email: Thomas Schmelzer <thomas.schmelzer@gmail.com>
License-File: LICENSE
Requires-Python: >=3.10
Requires-Dist: numpy>=2.2.3
Requires-Dist: pyarrow>=19.0.0
